{"type": "FeatureCollection", "features": [{"type": "Feature", "id": "PS_KIKONAI", "geometry": {"type": "Point", "coordinates": [140.434004, 41.677642]}, "properties": {"id": "PS_KIKONAI", "station_group_id": "SG_KIKONAI", "name_en": "Kikonai", "name_ja": "木古内", "label_rank": 50, "tags": ["normal", "shinkansen"]}}, {"type": "Feature", "id": "PS_SHIN_HAKODATE_HOKUTO", "geometry": {"type": "Point", "coordinates": [140.646525, 41.9054]}, "properties": {"id": "PS_SHIN_HAKODATE_HOKUTO", "station_group_id": "SG_SHIN_HAKODATE_HOKUTO", "name_en": "Shin-Hakodate-Hokuto", "name_ja": "新函館北斗", "label_rank": 100, "tags": ["hub", "shinkansen"]}}]}