{"type": "FeatureCollection", "features": [{"type": "Feature", "id": "PS_KORIYAMA", "geometry": {"type": "Point", "coordinates": [140.389363, 37.398187]}, "properties": {"id": "PS_KORIYAMA", "station_group_id": "SG_KORIYAMA", "name_en": "Koriyama", "name_ja": "郡山", "label_rank": 50, "tags": ["normal", "shinkansen"]}}]}