{"type": "FeatureCollection", "features": [{"type": "Feature", "id": "PS_HIMEJI", "geometry": {"type": "Point", "coordinates": [134.690769, 34.827659]}, "properties": {"id": "PS_HIMEJI", "station_group_id": "SG_HIMEJI", "name_en": "Himeji", "name_ja": "姫路", "label_rank": 100, "tags": ["hub", "shinkansen"]}}]}