{"type": "FeatureCollection", "features": [{"type": "Feature", "id": "PS_TAKEO_ONSEN", "geometry": {"type": "Point", "coordinates": [130.022322, 33.196151]}, "properties": {"id": "PS_TAKEO_ONSEN", "station_group_id": "SG_TAKEO_ONSEN", "name_en": "Takeo-Onsen", "name_ja": "武雄温泉", "label_rank": 100, "tags": ["hub", "shinkansen"]}}, {"type": "Feature", "id": "PS_URESHINO_ONSEN", "geometry": {"type": "Point", "coordinates": [129.99897222, 33.10655556]}, "properties": {"id": "PS_URESHINO_ONSEN", "station_group_id": "SG_URESHINO_ONSEN", "name_en": "Ureshino-Onsen", "name_ja": "嬉野温泉", "label_rank": 50, "tags": ["normal", "shinkansen"]}}]}