{"type": "FeatureCollection", "features": [{"type": "Feature", "id": "PS_IWATE_NUMAKUNAI", "geometry": {"type": "Point", "coordinates": [141.216955, 39.960155]}, "properties": {"id": "PS_IWATE_NUMAKUNAI", "station_group_id": "SG_IWATE_NUMAKUNAI", "name_en": "Iwate-Numakunai", "name_ja": "いわて沼宮内", "label_rank": 50, "tags": ["normal", "shinkansen"]}}]}