{"type": "FeatureCollection", "features": [{"type": "Feature", "id": "PS_KANAZAWA", "geometry": {"type": "Point", "coordinates": [136.648166, 36.578117]}, "properties": {"id": "PS_KANAZAWA", "station_group_id": "SG_KANAZAWA", "name_en": "Kanazawa", "name_ja": "金沢", "label_rank": 100, "tags": ["hub", "shinkansen"]}}]}