{"type": "FeatureCollection", "features": [{"type": "Feature", "id": "PS_FUKUI", "geometry": {"type": "Point", "coordinates": [136.223516, 36.062057]}, "properties": {"id": "PS_FUKUI", "station_group_id": "SG_FUKUI", "name_en": "Fukui", "name_ja": "福井", "label_rank": 100, "tags": ["hub", "shinkansen"]}}, {"type": "Feature", "id": "PS_ECHIZEN_TAKEFU", "geometry": {"type": "Point", "coordinates": [136.19888889, 35.89566667]}, "properties": {"id": "PS_ECHIZEN_TAKEFU", "station_group_id": "SG_ECHIZEN_TAKEFU", "name_en": "Echizen-Takefu", "name_ja": "越前たけふ", "label_rank": 50, "tags": ["normal", "shinkansen"]}}]}