{"type": "FeatureCollection", "features": [{"type": "Feature", "id": "PS_SHIN_MINAMATA", "geometry": {"type": "Point", "coordinates": [130.428893, 32.210825]}, "properties": {"id": "PS_SHIN_MINAMATA", "station_group_id": "SG_SHIN_MINAMATA", "name_en": "Shin-Minamata", "name_ja": "新水俣", "label_rank": 50, "tags": ["normal", "shinkansen"]}}, {"type": "Feature", "id": "PS_IZUMI", "geometry": {"type": "Point", "coordinates": [130.357803, 32.089275]}, "properties": {"id": "PS_IZUMI", "station_group_id": "SG_IZUMI", "name_en": "Izumi", "name_ja": "出水", "label_rank": 50, "tags": ["normal", "shinkansen"]}}]}