{"type": "FeatureCollection", "features": [{"type": "Feature", "id": "PS_SHIZUKUISHI", "geometry": {"type": "Point", "coordinates": [140.974762, 39.689244]}, "properties": {"id": "PS_SHIZUKUISHI", "station_group_id": "SG_SHIZUKUISHI", "name_en": "Shizukuishi", "name_ja": "雫石", "label_rank": 50, "tags": ["normal", "shinkansen"]}}, {"type": "Feature", "id": "PS_TAZAWAKO", "geometry": {"type": "Point", "coordinates": [140.722139, 39.700363]}, "properties": {"id": "PS_TAZAWAKO", "station_group_id": "SG_TAZAWAKO", "name_en": "Tazawako", "name_ja": "田沢湖", "label_rank": 50, "tags": ["normal", "shinkansen"]}}]}